{
  "timestamp": "2025-09-24T16:00:00Z",
  "general_check": {
    "workspace_root": "file:///Users/bshuler/Library/CloudStorage/OneDrive-Personal/cvideo-click-pave",
    "files_checked": 14,
    "files_with_errors": 0,
    "total_errors": 0,
    "error_details": {},
    "summary": "\u2705 No Pylance errors found!"
  },
  "typeddict_check": {
    "files_checked": 4,
    "typeddict_issues": [],
    "is_safe": true,
    "summary": "\u2705 All files are TypedDict safe!"
  },
  "overall_status": "\u2705 PASS"
}